<annotation><folder>./workspace/mobile/images/multi_lines/</folder><filename>li_151.png</filename><path>./workspace/mobile/images/multi_lines//imgs/li_151.png</path><source><database>unknown</database></source><size><width>400</width><height>400</height></size><segmented>0</segmented><_object><name>li_151</name><pose>Unspecified</pose><lengths><l_0>388.113659443658</l_0><l_1>164.28862916617803</l_1><l_2>266.83041100254934</l_2></lengths><truncated>0</truncated><difficult>0</difficult><bndboxs><b_0><xmin>68.39504063198531</xmin><ymin>283.12182697081346</ymin><xmax>383.4604182324813</xmax><ymax>60.15774290277274</ymax></b_0><b_1><xmin>167.43628119372272</xmin><ymin>4.972901732734725</ymin><xmax>161.15720225272256</xmax><ymax>136.73581802870723</ymax></b_1><b_2><xmin>378.7525758894722</xmin><ymin>113.23808853265058</ymin><xmax>67.57597496420927</xmax><ymax>94.04341230584863</ymax></b_2></bndboxs></_object></annotation>