<annotation><folder>./workspace/mobile/images/multi_lines/</folder><filename>li_3278.png</filename><path>./workspace/mobile/images/multi_lines//imgs/li_3278.png</path><source><database>unknown</database></source><size><width>400</width><height>400</height></size><segmented>0</segmented><_object><name>li_3278</name><pose>Unspecified</pose><lengths><l_0>105.0025771125668</l_0><l_1>271.525326342468</l_1></lengths><truncated>0</truncated><difficult>0</difficult><bndboxs><b_0><xmin>204.19986566802368</xmin><ymin>106.53924410974041</ymin><xmax>49.93655533696568</xmax><ymax>11.36267561077906</ymax></b_0><b_1><xmin>7.692495269409871</xmin><ymin>272.9141957079051</ymin><xmax>100.95674376835552</xmax><ymax>42.78929185668217</ymax></b_1></bndboxs></_object></annotation>