<annotation><folder>./workspace/mobile/images/multi_lines/</folder><filename>li_4882.png</filename><path>./workspace/mobile/images/multi_lines//imgs/li_4882.png</path><source><database>unknown</database></source><size><width>400</width><height>400</height></size><segmented>0</segmented><_object><name>li_4882</name><pose>Unspecified</pose><lengths><l_0>326.40184365382373</l_0><l_1>83.3309847436702</l_1></lengths><truncated>0</truncated><difficult>0</difficult><bndboxs><b_0><xmin>287.22443699963196</xmin><ymin>35.81459620393632</ymin><xmax>328.3987452234462</xmax><ymax>120.2371361508361</ymax></b_0><b_1><xmin>172.16341158961237</xmin><ymin>101.59449747722822</ymin><xmax>282.6089525642243</xmax><ymax>326.92691031668335</ymax></b_1></bndboxs></_object></annotation>