<annotation><folder>./workspace/mobile/images/multi_lines/</folder><filename>li_539.png</filename><path>./workspace/mobile/images/multi_lines//imgs/li_539.png</path><source><database>unknown</database></source><size><width>400</width><height>400</height></size><segmented>0</segmented><_object><name>li_539</name><pose>Unspecified</pose><lengths><l_0>255.09972196486106</l_0><l_1>187.97611072764852</l_1><l_2>195.89407587588545</l_2></lengths><truncated>0</truncated><difficult>0</difficult><bndboxs><b_0><xmin>61.831377344142794</xmin><ymin>270.0499844526776</ymin><xmax>114.30987731451987</xmax><ymax>261.6899295615286</ymax></b_0><b_1><xmin>348.0387187537165</xmin><ymin>184.21593065302196</ymin><xmax>149.25129113792838</xmax><ymax>241.43107364585202</ymax></b_1><b_2><xmin>366.47719706109496</xmin><ymin>235.63115755085624</ymin><xmax>44.78420251427133</xmax><ymax>190.57104316785095</ymax></b_2></bndboxs></_object></annotation>