<annotation><folder>./workspace/mobile/images/multi_lines/</folder><filename>li_1314.png</filename><path>./workspace/mobile/images/multi_lines//imgs/li_1314.png</path><source><database>unknown</database></source><size><width>400</width><height>400</height></size><segmented>0</segmented><_object><name>li_1314</name><pose>Unspecified</pose><lengths><l_0>214.99559922145153</l_0><l_1>214.9965057135907</l_1></lengths><truncated>0</truncated><difficult>0</difficult><bndboxs><b_0><xmin>284.6483489223692</xmin><ymin>89.08792350871218</ymin><xmax>206.78271085853353</xmax><ymax>296.10923377653637</ymax></b_0><b_1><xmin>308.840719525923</xmin><ymin>242.10218266461553</ymin><xmax>281.5327080265199</xmax><ymax>77.15691404233516</ymax></b_1></bndboxs></_object></annotation>