<annotation><folder>./workspace/mobile/images/multi_lines/</folder><filename>li_2222.png</filename><path>./workspace/mobile/images/multi_lines//imgs/li_2222.png</path><source><database>unknown</database></source><size><width>400</width><height>400</height></size><segmented>0</segmented><_object><name>li_2222</name><pose>Unspecified</pose><lengths><l_0>118.47076935875313</l_0><l_1>137.56294326281105</l_1></lengths><truncated>0</truncated><difficult>0</difficult><bndboxs><b_0><xmin>47.48144985052196</xmin><ymin>157.0581786612296</ymin><xmax>90.24186792645258</xmax><ymax>135.27811661125662</ymax></b_0><b_1><xmin>346.0530711567889</xmin><ymin>295.7416946066991</ymin><xmax>103.09678915838197</xmax><ymax>231.12931919962753</ymax></b_1></bndboxs></_object></annotation>