<annotation><folder>./workspace/mobile/images/multi_lines/</folder><filename>li_3770.png</filename><path>./workspace/mobile/images/multi_lines//imgs/li_3770.png</path><source><database>unknown</database></source><size><width>400</width><height>400</height></size><segmented>0</segmented><_object><name>li_3770</name><pose>Unspecified</pose><lengths><l_0>156.79557660917433</l_0><l_1>78.17501340561572</l_1></lengths><truncated>0</truncated><difficult>0</difficult><bndboxs><b_0><xmin>190.56618148841352</xmin><ymin>137.26973443740755</ymin><xmax>267.1153623280413</xmax><ymax>119.65573539258894</ymax></b_0><b_1><xmin>177.31295317663503</xmin><ymin>253.63579003696285</ymin><xmax>325.46761780241116</xmax><ymax>342.3838021996085</ymax></b_1></bndboxs></_object></annotation>