<annotation><folder>./workspace/mobile/images/multi_lines/</folder><filename>li_62.png</filename><path>./workspace/mobile/images/multi_lines//imgs/li_62.png</path><source><database>unknown</database></source><size><width>400</width><height>400</height></size><segmented>0</segmented><_object><name>li_62</name><pose>Unspecified</pose><lengths><l_0>242.0812396694701</l_0><l_1>92.88814427015654</l_1></lengths><truncated>0</truncated><difficult>0</difficult><bndboxs><b_0><xmin>17.762495628593022</xmin><ymin>236.5680560203669</ymin><xmax>245.13358280067138</xmax><ymax>141.56016274731385</ymax></b_0><b_1><xmin>282.32704027209945</xmin><ymin>346.11907812068904</ymin><xmax>108.6908662692172</xmax><ymax>41.17210403917086</ymax></b_1></bndboxs></_object></annotation>